sdc_api/__init__.py
sdc_api/sdc_api.py
sdc_api-0.2.1.dist-info/METADATA
sdc_api-0.2.1.dist-info/WHEEL
sdc_api-0.2.1.dist-info/top_level.txt
sdc_api-0.2.1.dist-info/RECORD
