Metadata-Version: 2.1
Name: sdc-api
Version: 0.2.1
Summary: An async wrapper for Server-Discord.Com API
Home-page: https://github.com/TomoriBot/sdc_api
Author: Tomori Project
Author-email: dev@discord.band
License: UNKNOWN
Platform: UNKNOWN
Classifier: Programming Language :: Python :: 3
Classifier: License :: OSI Approved :: MIT License
Classifier: Operating System :: OS Independent
